README.md
setup.py
cortex/__init__.py
cortex/client.py
cortex/exceptions.py
cortex/binary/__init__.py
cortex_deploy.egg-info/PKG-INFO
cortex_deploy.egg-info/SOURCES.txt
cortex_deploy.egg-info/dependency_links.txt
cortex_deploy.egg-info/entry_points.txt
cortex_deploy.egg-info/top_level.txt