Metadata-Version: 2.1
Name: cortex-deploy
Version: 0.20.0.dev0
Summary: Model serving at scale
Home-page: https://www.cortex.dev
Author: cortex.dev
Author-email: dev@cortex.dev
License: Apache License 2.0
Project-URL: Bug Reports, https://github.com/cortexlabs/cortex/issues
Project-URL: Chat with us, https://gitter.im/cortexlabs/cortex
Project-URL: Documentation, https://docs.cortex.dev
Project-URL: Source Code, https://github.com/cortexlabs/cortex
Platform: UNKNOWN
Classifier: Operating System :: MacOS
Classifier: Operating System :: POSIX :: Linux
Classifier: Programming Language :: Python :: 3.6
Classifier: Programming Language :: Python :: 3.7
Classifier: Programming Language :: Python :: 3.8
Classifier: Intended Audience :: Developers
Requires-Python: >=3.6.1
